dbip/__init__.py
dbip/dbip.py
python_dbip-22.8.31.dist-info/METADATA
python_dbip-22.8.31.dist-info/WHEEL
python_dbip-22.8.31.dist-info/top_level.txt
python_dbip-22.8.31.dist-info/RECORD
