Metadata-Version: 2.1
Name: python-dbip
Version: 22.8.31
Summary: This is an IP database with verification and supports IP dual stack protocol
Home-page: https://mengyuns.com
Author: mxlbb(萌小狸宝宝)
Author-email: admin@mengyuns.com
Maintainer: mxlbb(萌小狸宝宝)
Maintainer-email: admin@mengyuns.com
Classifier: Programming Language :: Python :: 3
Classifier: Operating System :: OS Independent
Requires-Python: >=3.7
